up2minio.py
up2minio-0.0.2.dist-info/LICENSE
up2minio-0.0.2.dist-info/METADATA
up2minio-0.0.2.dist-info/WHEEL
up2minio-0.0.2.dist-info/top_level.txt
up2minio-0.0.2.dist-info/RECORD
