Metadata-Version: 2.1
Name: up2minio
Version: 0.0.2
Summary: 将图片上传至 Minio 的扩展模块
Home-page: https://www.dfql.io
Author: daofengqianlin
License: Apache 2.0
Keywords: sapic minio storage hook
Classifier: Development Status :: 4 - Beta
Classifier: Intended Audience :: Developers
Classifier: License :: OSI Approved :: Apache Software License
Classifier: Programming Language :: Python
Classifier: Programming Language :: Python :: 3
Classifier: Programming Language :: Python :: 3.6
Classifier: Programming Language :: Python :: 3.7
Classifier: Programming Language :: Python :: 3.8
Classifier: Programming Language :: Python :: 3.9
Classifier: Programming Language :: Python :: 3.10
Classifier: Topic :: Software Development :: Libraries
Classifier: Topic :: Multimedia :: Graphics
Requires-Python: >=3.6
License-File: LICENSE
Requires-Dist: minio>=7.1.10
